HongTaQuant/__init__.py
HongTaQuant/HongTaData/__init__.py
HongTaQuant/HongTaData/config/__init__.py
HongTaQuant/HongTaData/config/settings.py
HongTaQuant/HongTaData/http/__init__.py
HongTaQuant/HongTaData/http/client.py
HongTaQuant/HongTaData/models/__init__.py
HongTaQuant/HongTaData/models/market_data.py
HongTaQuant/utils/__init__.py
HongTaQuant/utils/hosts.py
hongtaquant-0.1.3.dist-info/METADATA
hongtaquant-0.1.3.dist-info/WHEEL
hongtaquant-0.1.3.dist-info/RECORD
