Metadata-Version: 2.4
Name: HongTaQuant
Version: 0.1.3
Summary: HongTaQuant是基于红塔证券量化衍生出来的一套Python框架，对外以Python库的形式提供策略交易所需要的行情和相关的API接口。
Author: HongTa Stock Quant Team
Keywords: data,finance,http,kafka,sdk,streaming
Requires-Python: >=3.8
Requires-Dist: confluent-kafka>=2.12.1
Requires-Dist: httpx>=0.25.0
Requires-Dist: pydantic-settings>=2.0.0
Requires-Dist: pydantic>=2.0.0
Requires-Dist: tenacity>=8.2.0
Provides-Extra: dev
Requires-Dist: mypy>=1.5.0; extra == 'dev'
Requires-Dist: pytest-asyncio>=0.21.0; extra == 'dev'
Requires-Dist: pytest-cov>=4.1.0; extra == 'dev'
Requires-Dist: pytest-mock>=3.11.0; extra == 'dev'
Requires-Dist: pytest>=7.4.0; extra == 'dev'
Requires-Dist: ruff>=0.1.0; extra == 'dev'
